crested/__init__.py
crested/_backend.py
crested/_conf.py
crested/_datasets.py
crested/_genome.py
crested/_io.py
crested/pl/__init__.py
crested/pl/_utils.py
crested/pl/bar/__init__.py
crested/pl/bar/_normalization_weights.py
crested/pl/bar/_region.py
crested/pl/heatmap/__init__.py
crested/pl/heatmap/_correlations.py
crested/pl/hist/__init__.py
crested/pl/hist/_distribution.py
crested/pl/locus/__init__.py
crested/pl/locus/_locus_scoring.py
crested/pl/locus/_track.py
crested/pl/patterns/__init__.py
crested/pl/patterns/_contribution_scores.py
crested/pl/patterns/_enhancer_design.py
crested/pl/patterns/_modisco_results.py
crested/pl/patterns/_utils.py
crested/pl/scatter/__init__.py
crested/pl/scatter/_class_density.py
crested/pl/violin/__init__.py
crested/pl/violin/_correlations.py
crested/pp/__init__.py
crested/pp/_filter.py
crested/pp/_normalization.py
crested/pp/_regions.py
crested/pp/_split.py
crested/pp/_utils.py
crested/tl/__init__.py
crested/tl/_configs.py
crested/tl/_crested.py
crested/tl/_explainer.py
crested/tl/_explainer_tf.py
crested/tl/_explainer_torch.py
crested/tl/_tools.py
crested/tl/_utils.py
crested/tl/data/__init__.py
crested/tl/data/_anndatamodule.py
crested/tl/data/_dataloader.py
crested/tl/data/_dataset.py
crested/tl/losses/__init__.py
crested/tl/losses/_cosinemse.py
crested/tl/losses/_cosinemse_log.py
crested/tl/losses/_poisson.py
crested/tl/losses/_poissonmultinomial.py
crested/tl/metrics/__init__.py
crested/tl/metrics/_concordancecorr.py
crested/tl/metrics/_pearsoncorr.py
crested/tl/metrics/_pearsoncorrlog.py
crested/tl/metrics/_spearmancorr.py
crested/tl/metrics/_zeropenalty.py
crested/tl/modisco/__init__.py
crested/tl/modisco/_modisco_utils.py
crested/tl/modisco/_tfmodisco.py
crested/tl/zoo/__init__.py
crested/tl/zoo/_basenji.py
crested/tl/zoo/_borzoi.py
crested/tl/zoo/_deeptopic_cnn.py
crested/tl/zoo/_deeptopic_lstm.py
crested/tl/zoo/_dilated_cnn.py
crested/tl/zoo/_dilated_cnn_decoupled.py
crested/tl/zoo/_enformer.py
crested-1.6.1.dist-info/METADATA
crested-1.6.1.dist-info/WHEEL
crested-1.6.1.dist-info/licenses/LICENSE
crested-1.6.1.dist-info/RECORD
