Metadata-Version: 2.4
Name: crested
Version: 1.6.1
Summary: CREsted: Cis-Regulatory Element Sequence Training, Explanation, and Design
Project-URL: Documentation, https://crested.readthedocs.io/
Project-URL: Home-page, https://github.com/aertslab/crested/
Project-URL: Source, https://github.com/aertslab/crested/
Author: Stein Aerts Lab
Maintainer-email: Lukas Mahieu <lukas.mahieu@kuleuven.be>
License: 
License-File: LICENSE
Classifier: Programming Language :: Python :: 3 :: Only
Classifier: Programming Language :: Python :: 3.11
Classifier: Programming Language :: Python :: 3.12
Classifier: Programming Language :: Python :: 3.13
Requires-Python: <3.14,>=3.11
Requires-Dist: anndata
Requires-Dist: biothings-client<0.4
Requires-Dist: keras>=3.4
Requires-Dist: logomaker
Requires-Dist: loguru
Requires-Dist: numpy
Requires-Dist: pandas
Requires-Dist: pooch
Requires-Dist: pybigtools>=0.2
Requires-Dist: pysam
Requires-Dist: scanpy>=1.10
Requires-Dist: scikit-learn
Requires-Dist: seaborn
Requires-Dist: tqdm
Requires-Dist: wandb>=0.12.10
Provides-Extra: dev
Requires-Dist: pre-commit; extra == 'dev'
Requires-Dist: pytest; extra == 'dev'
Requires-Dist: twine>=4.0.2; extra == 'dev'
Provides-Extra: doc
Requires-Dist: docutils!=0.18.*,!=0.19.*,>=0.8; extra == 'doc'
Requires-Dist: ipykernel; extra == 'doc'
Requires-Dist: ipython; extra == 'doc'
Requires-Dist: modisco-lite; extra == 'doc'
Requires-Dist: myst-nb; extra == 'doc'
Requires-Dist: pandas; extra == 'doc'
Requires-Dist: ruff; extra == 'doc'
Requires-Dist: sphinx-autodoc-typehints; extra == 'doc'
Requires-Dist: sphinx-book-theme>=1; extra == 'doc'
Requires-Dist: sphinx-copybutton; extra == 'doc'
Requires-Dist: sphinx>=4; extra == 'doc'
Requires-Dist: sphinxcontrib-bibtex>=1; extra == 'doc'
Requires-Dist: sphinxext-opengraph; extra == 'doc'
Requires-Dist: tensorflow; extra == 'doc'
Provides-Extra: motif
Requires-Dist: memelite; (python_version < '3.13') and extra == 'motif'
Requires-Dist: modisco-lite>=2.2.1; extra == 'motif'
Provides-Extra: test
Requires-Dist: anndata; extra == 'test'
Requires-Dist: coverage; extra == 'test'
Requires-Dist: pytest; extra == 'test'
Requires-Dist: pytest-cov; extra == 'test'
